invasync/__init__.py
invasync/__main__.py
invasync/json_utils.py
invasync/models/__init__.py
invasync/models/user.py
invasync-3.0.0.dist-info/METADATA
invasync-3.0.0.dist-info/WHEEL
invasync-3.0.0.dist-info/entry_points.txt
invasync-3.0.0.dist-info/RECORD
