Metadata-Version: 2.4
Name: invasync
Version: 3.0.0
Summary: Invaders synchronizer
Project-URL: repository, https://github.com/0xNoNames/InvaSync
Author-email: 0xNoNames <xnonames@proton.me>
Requires-Python: >=3.9
Requires-Dist: beautifulsoup4>=4.13.4
Requires-Dist: httpx>=0.28.1
